ml4k/__init__.py
ml4k/errors.py
ml4k-0.7.dist-info/LICENSE.txt
ml4k-0.7.dist-info/METADATA
ml4k-0.7.dist-info/WHEEL
ml4k-0.7.dist-info/top_level.txt
ml4k-0.7.dist-info/RECORD
